{"Airoli": {"value": 157, "color": "#ff9800", "updated": "22:58"}, "Vashi": {"value": 122, "color": "#ffeb3b", "updated": "22:58"}, "Nerul": {"value": 132, "color": "#ffeb3b", "updated": "22:58"}, "Kharghar": {"value": 111, "color": "#ffeb3b", "updated": "22:58"}, "Belapur": {"value": 128, "color": "#ffeb3b", "updated": "22:58"}, "Seawoods": {"value": 97, "color": "#81c784", "updated": "22:58"}, "Ulwe": {"value": 124, "color": "#ffeb3b", "updated": "22:58"}, "Sanpada": {"value": 110, "color": "#ffeb3b", "updated": "22:58"}, "Kopar Khairane": {"value": 121, "color": "#ffeb3b", "updated": "22:58"}}