{"Airoli": {"value": 144, "color": "#ffeb3b", "updated": "22:53"}, "Vashi": {"value": 151, "color": "#ff9800", "updated": "22:53"}, "Nerul": {"value": 133, "color": "#ffeb3b", "updated": "22:53"}, "Kharghar": {"value": 144, "color": "#ffeb3b", "updated": "22:53"}, "Belapur": {"value": 122, "color": "#ffeb3b", "updated": "22:53"}, "Seawoods": {"value": 140, "color": "#ffeb3b", "updated": "22:53"}, "Ulwe": {"value": 123, "color": "#ffeb3b", "updated": "22:53"}, "Sanpada": {"value": 151, "color": "#ff9800", "updated": "22:53"}, "Kopar Khairane": {"value": 137, "color": "#ffeb3b", "updated": "22:53"}}